balethon/__init__.py
balethon/smart_call.py
balethon/sync_support.py
balethon/client/__init__.py
balethon/client/client.py
balethon/client/attachments/__init__.py
balethon/client/attachments/get_file.py
balethon/client/attachments/send_animation.py
balethon/client/attachments/send_audio.py
balethon/client/attachments/send_contact.py
balethon/client/attachments/send_document.py
balethon/client/attachments/send_location.py
balethon/client/attachments/send_media_group.py
balethon/client/attachments/send_photo.py
balethon/client/attachments/send_sticker.py
balethon/client/attachments/send_video.py
balethon/client/attachments/send_voice.py
balethon/client/chats/__init__.py
balethon/client/chats/ban_chat_member.py
balethon/client/chats/delete_chat_photo.py
balethon/client/chats/get_chat.py
balethon/client/chats/get_chat_administrators.py
balethon/client/chats/get_chat_member.py
balethon/client/chats/get_chat_members_count.py
balethon/client/chats/leave_chat.py
balethon/client/chats/pin_chat_message.py
balethon/client/chats/promote_chat_member.py
balethon/client/chats/restrict_chat_member.py
balethon/client/chats/send_chat_action.py
balethon/client/chats/set_chat_description.py
balethon/client/chats/set_chat_photo.py
balethon/client/chats/set_chat_title.py
balethon/client/chats/unban_chat_member.py
balethon/client/chats/unpin_all_chat_messages.py
balethon/client/chats/unpin_chat_message.py
balethon/client/invite_links/__init__.py
balethon/client/invite_links/create_chat_invite_link.py
balethon/client/invite_links/export_chat_invite_link.py
balethon/client/invite_links/revoke_chat_invite_link.py
balethon/client/messages/__init__.py
balethon/client/messages/answer_callback_query.py
balethon/client/messages/copy_message.py
balethon/client/messages/delete_message.py
balethon/client/messages/edit_message_caption.py
balethon/client/messages/edit_message_reply_markup.py
balethon/client/messages/edit_message_text.py
balethon/client/messages/forward_message.py
balethon-1.1.0.dist-info/licenses/LICENSE
balethon-1.1.0.dist-info/METADATA
balethon-1.1.0.dist-info/WHEEL
balethon-1.1.0.dist-info/top_level.txt
balethon-1.1.0.dist-info/RECORD
